{
  "users": [
    {
      "id": "58a2",
      "email": "sachin@test.com",
      "name": "sachin",
      "password": "abc@123"
    },
    {
      "id": "1ed9",
      "email": "rahul@test.com",
      "password": "abc@123",
      "name": "rahul"
    },
    {
      "id": "3350",
      "email": "babu@test.com",
      "password": "abc@123",
      "name": "babu"
    },
    {
      "id": "0463",
      "email": "rahul@test.com",
      "password": "xyz@123",
      "name": "rahul"
    },
    {
      "id": "8aab",
      "email": "virender@test.com",
      "password": "poi@987",
      "name": "virender"
    },
    {
      "id": "3d28",
      "email": "yuvraj@singh.com",
      "password": "six6's",
      "name": "yuvraj"
    },
    {
      "id": "723c",
      "email": "yuvraj@singh.com",
      "password": "six6's",
      "name": "yuvraj"
    },
    {
      "id": "49d5",
      "email": "ramesh@test.com",
      "password": "ramesh123",
      "name": "ramesh"
    },
    {
      "id": "9aaa",
      "email": "suresh@test.com",
      "password": "qwert@123",
      "name": "suresh"
    },
    {
      "id": "0fb8",
      "email": "john@connor.com",
      "password": "terminator",
      "name": "John"
    }
  ],
  "restaurants": [
    {
      "id": "1",
      "name": "Pizza Hut",
      "contact": "1234",
      "address": "Karol Bagh"
    },
    {
      "id": "2",
      "name": "CCD",
      "contact": "5678",
      "address": "Rajendra Nagar"
    },
    {
      "id": "3",
      "name": "Barbeque Nation",
      "contact": "9012",
      "address": "Hauz Khas"
    },
    {
      "id": "3933",
      "name": "ZamZam ",
      "contact": "7954",
      "address": "tvm"
    },
    {
      "id": "6754",
      "name": "Starbucks",
      "address": "Delhi",
      "contact": "111000"
    },
    {
      "id": "f39e",
      "name": "Biryani House",
      "address": "CP",
      "contact": "233432"
    }
  ]
}